shot_detector/__init__.py
shot_detector/tool.py
shot_detector/detectors/__init__.py
shot_detector/detectors/base_shot_detector.py
shot_detector/detectors/common_detector.py
shot_detector/detectors/dummy_text_detector.py
shot_detector/detectors/simple_detector.py
shot_detector/features/__init__.py
shot_detector/features/extractors/__init__.py
shot_detector/features/extractors/base_extractor.py
shot_detector/features/extractors/image_based.py
shot_detector/features/extractors/parallel_extractor.py
shot_detector/features/extractors/vector_based.py
shot_detector/features/extractors/colours/__init__.py
shot_detector/features/extractors/colours/bw_extractor.py
shot_detector/features/extractors/colours/long_luma_extractor.py
shot_detector/features/extractors/colours/luma_extractor.py
shot_detector/features/extractors/colours/rgb_extractor.py
shot_detector/features/extractors/colours/rgbbw_extractor.py
shot_detector/features/extractors/features/__init__.py
shot_detector/features/extractors/features/dct.py
shot_detector/features/extractors/features/histogram.py
shot_detector/features/extractors/features/optical_flow.py
shot_detector/features/metrics/__init__.py
shot_detector/features/norms/__init__.py
shot_detector/features/norms/base_norm.py
shot_detector/features/norms/l1_norm.py
shot_detector/features/norms/l2_norm.py
shot_detector/filters/__init__.py
shot_detector/filters/angle_change_filter.py
shot_detector/filters/base_filter.py
shot_detector/filters/base_filter_wrapper.py
shot_detector/filters/base_nested_filter.py
shot_detector/filters/bound_filter.py
shot_detector/filters/colour_filter.py
shot_detector/filters/condition_filter.py
shot_detector/filters/dct_filter.py
shot_detector/filters/delay_filter.py
shot_detector/filters/dht_filter.py
shot_detector/filters/exp_filter.py
shot_detector/filters/factor_filter.py
shot_detector/filters/filter.py
shot_detector/filters/filter_cast_features.py
shot_detector-0.0.5.dev3.dist-info/DESCRIPTION.rst
shot_detector-0.0.5.dev3.dist-info/METADATA
shot_detector-0.0.5.dev3.dist-info/RECORD
shot_detector-0.0.5.dev3.dist-info/WHEEL
shot_detector-0.0.5.dev3.dist-info/entry_points.txt
shot_detector-0.0.5.dev3.dist-info/metadata.json
shot_detector-0.0.5.dev3.dist-info/top_level.txt
