Metadata-Version: 2.0
Name: shot-detector
Version: 0.0.5.dev3
Summary: Python shot detector based on PyAV
Home-page: UNKNOWN
Author: Ilya w495 Nikitin
Author-email: w@w-495.ru
License: BSD
Keywords: video-processing image-processing video
Platform: UNKNOWN
Classifier: Development Status :: 2 - Pre-Alpha
Classifier: Environment :: Console
Classifier: Intended Audience :: Developers
Classifier: Intended Audience :: Education
Classifier: Intended Audience :: Information Technology
Classifier: Intended Audience :: Science/Research
Classifier: Intended Audience :: Telecommunications Industry
Classifier: License :: OSI Approved :: BSD License
Classifier: Natural Language :: English
Classifier: Natural Language :: Russian
Classifier: Topic :: Multimedia :: Graphics :: Capture
Classifier: Topic :: Multimedia :: Video :: Capture
Classifier: Topic :: Multimedia :: Video :: Non-Linear Editor
Classifier: Topic :: Scientific/Engineering :: Artificial Intelligence
Classifier: Topic :: Scientific/Engineering :: Information Analysis
Classifier: Topic :: Scientific/Engineering :: Mathematics
Classifier: Topic :: Utilities
Requires-Dist: HeapDict (==1.0.0)
Requires-Dist: Jinja2 (==2.8)
Requires-Dist: MarkupSafe (==0.23)
Requires-Dist: Pillow (==3.3.1)
Requires-Dist: PyYAML (==3.11)
Requires-Dist: av (==0.2.3)
Requires-Dist: backports-abc (==0.4)
Requires-Dist: bokeh (==0.12.1)
Requires-Dist: chest (==0.2.3)
Requires-Dist: cloudpickle (==0.2.1)
Requires-Dist: colorlog (==2.7.0)
Requires-Dist: cycler (==0.10.0)
Requires-Dist: dask (==0.11.0)
Requires-Dist: decorator (==4.0.10)
Requires-Dist: dill (==0.2.5)
Requires-Dist: future (==0.15.2)
Requires-Dist: gevent (==1.1.2)
Requires-Dist: greenlet (==0.4.10)
Requires-Dist: locket (==0.2.0)
Requires-Dist: matplotlib (==1.5.1)
Requires-Dist: networkx (==1.11)
Requires-Dist: numpy (==1.11.1)
Requires-Dist: pandas (==0.18.1)
Requires-Dist: partd (==0.3.6)
Requires-Dist: pymp-pypi (==0.2)
Requires-Dist: pyparsing (==2.1.4)
Requires-Dist: python-dateutil (==2.5.3)
Requires-Dist: pytz (==2016.6.1)
Requires-Dist: requests (==2.11.1)
Requires-Dist: scikit-image (==0.12.3)
Requires-Dist: scikit-learn (==0.17.1)
Requires-Dist: scipy (==0.18.0)
Requires-Dist: six (==1.10.0)
Requires-Dist: toolz (==0.8.0)
Requires-Dist: tornado (==4.4.1)
Requires-Dist: typing (==3.5.2.2)
